quartet_manifest/__init__.py
quartet_manifest/apps.py
quartet_manifest/models.py
quartet_manifest/urls.py
quartet_manifest/views.py
quartet_manifest/inspection/__init__.py
quartet_manifest/inspection/inspectors.py
quartet_manifest-1.0.5.dist-info/METADATA
quartet_manifest-1.0.5.dist-info/RECORD
quartet_manifest-1.0.5.dist-info/WHEEL
quartet_manifest-1.0.5.dist-info/top_level.txt
tests/__init__.py
tests/settings.py
tests/test_views.py
tests/urls.py
