Metadata-Version: 2.1
Name: quartet-manifest
Version: 1.0.5
Summary: Reports back configuration and capabilities to quartet-ui.
Home-page: https://gitlab.com/serial-lab/quartet_manifest
Author: SerialLab Corp
Author-email: slab@serial-lab.com
License: GPLv3
Keywords: quartet_manifest
Platform: UNKNOWN
Classifier: Development Status :: 3 - Alpha
Classifier: Framework :: Django
Classifier: Framework :: Django :: 1.8
Classifier: Framework :: Django :: 1.9
Classifier: Framework :: Django :: 1.10
Classifier: Framework :: Django :: 2.0
Classifier: Intended Audience :: Developers
Classifier: License :: OSI Approved :: GNU General Public License v3 (GPLv3)
Classifier: Natural Language :: English
Classifier: Programming Language :: Python :: 3
Classifier: Programming Language :: Python :: 3.3
Classifier: Programming Language :: Python :: 3.4
Classifier: Programming Language :: Python :: 3.5
Classifier: Programming Language :: Python :: 3.6
